soloway_unofficial/__init__.py
soloway_unofficial/client.py
soloway_unofficial-1.1.0.dist-info/LICENSE
soloway_unofficial-1.1.0.dist-info/WHEEL
soloway_unofficial-1.1.0.dist-info/METADATA
soloway_unofficial-1.1.0.dist-info/RECORD
