Metadata-Version: 2.1
Name: soloway-unofficial
Version: 1.1.0
Summary: Простейшая реализация SDK для https://dsp.soloway.ru/
Home-page: https://github.com/ZFullio/soloway-unofficial
License: MIT
Author: viktor
Author-email: vi.dave@yandex.ru
Requires-Python: >=3.10,<4.0
Classifier: License :: OSI Approved :: MIT License
Classifier: Programming Language :: Python :: 3
Classifier: Programming Language :: Python :: 3.10
Requires-Dist: requests (>=2.28.1,<3.0.0)
Requires-Dist: tqdm (>=4.64.1,<5.0.0)
Project-URL: Repository, https://github.com/ZFullio/soloway-unofficial
